spannerelixir/__init__.py
spannerelixir/exceptions.py
spannerelixir/fields.py
spannerelixir/model.py
spannerelixir/query.py
spannerelixir/session.py
spannerelixir/utils.py
spannerelixir-0.1.15.dist-info/METADATA
spannerelixir-0.1.15.dist-info/WHEEL
spannerelixir-0.1.15.dist-info/top_level.txt
spannerelixir-0.1.15.dist-info/RECORD
